simple_stories_train/__init__.py
simple_stories_train/dataloaders.py
simple_stories_train/log.py
simple_stories_train/tinyshakespeare.py
simple_stories_train/tokenizer.py
simple_stories_train/train_gpt2.py
simple_stories_train/train_llama.py
simple_stories_train/utils.py
simple_stories_train/models/llama.py
simple_stories_train/models/model_configs.py
simple_stories_train-0.0.1.dist-info/licenses/LICENSE
simple_stories_train-0.0.1.dist-info/METADATA
simple_stories_train-0.0.1.dist-info/WHEEL
simple_stories_train-0.0.1.dist-info/top_level.txt
simple_stories_train-0.0.1.dist-info/RECORD
