Metadata-Version: 2.4
Name: simple_stories_train
Version: 0.0.1
Summary: Training of small LM models for SimpleStories
Requires-Python: >=3.11
License-File: LICENSE
Requires-Dist: torch<2.6.0
Requires-Dist: torchvision
Requires-Dist: pydantic
Requires-Dist: wandb
Requires-Dist: fire
Requires-Dist: tqdm
Requires-Dist: pytest
Requires-Dist: ipykernel
Requires-Dist: jaxtyping
Requires-Dist: tiktoken
Requires-Dist: transformers
Requires-Dist: datasets
Requires-Dist: python-dotenv
Provides-Extra: dev
Requires-Dist: ruff; extra == "dev"
Requires-Dist: pyright; extra == "dev"
Requires-Dist: pre-commit; extra == "dev"
Dynamic: license-file
